webeater/__init__.py
webeater/__main__.py
webeater/config.py
webeater/eater.py
webeater/extracting.py
webeater/log.py
webeater/rendering.py
webeater/util.py
webeater/hints/default.json
webeater/hints/news.json
webeater/hints/sports.json
webeater/thirdparty/__init__.py
webeater/thirdparty/beautifulsoup.py
webeater/thirdparty/selenium.py
webeater-0.1.1.dist-info/licenses/LICENSE
webeater-0.1.1.dist-info/METADATA
webeater-0.1.1.dist-info/WHEEL
webeater-0.1.1.dist-info/entry_points.txt
webeater-0.1.1.dist-info/top_level.txt
webeater-0.1.1.dist-info/RECORD
