Metadata-Version: 2.4
Name: webeater
Version: 0.1.1
Summary: A web content extraction tool designed to fetch and process web pages efficiently
Author-email: Tiago Ribeiro <webeater@tiagoribeiro.pt>
Maintainer-email: Tiago Ribeiro <webeater@tiagoribeiro.pt>
License-Expression: MIT
Project-URL: Homepage, https://github.com/tiagrib/webeater
Project-URL: Repository, https://github.com/tiagrib/webeater.git
Project-URL: Issues, https://github.com/tiagrib/webeater/issues
Project-URL: Documentation, https://github.com/tiagrib/webeater#readme
Keywords: web,scraping,extraction,selenium,beautifulsoup,content
Classifier: Development Status :: 3 - Alpha
Classifier: Environment :: Console
Classifier: Environment :: Web Environment
Classifier: Intended Audience :: Developers
Classifier: Intended Audience :: Information Technology
Classifier: Natural Language :: English
Classifier: Operating System :: OS Independent
Classifier: Programming Language :: Python :: 3.9
Classifier: Programming Language :: Python :: 3.10
Classifier: Programming Language :: Python :: 3.11
Classifier: Programming Language :: Python :: 3.12
Classifier: Topic :: Internet :: WWW/HTTP
Classifier: Topic :: Internet :: WWW/HTTP :: Browsers
Classifier: Topic :: Software Development :: Libraries :: Python Modules
Classifier: Topic :: Text Processing :: Markup :: HTML
Classifier: Topic :: Utilities
Classifier: Typing :: Typed
Requires-Python: >=3.9
License-File: LICENSE
Requires-Dist: annotated-types>=0.7.0
Requires-Dist: attrs>=25.3.0
Requires-Dist: beautifulsoup4>=4.13.4
Requires-Dist: bs4>=0.0.2
Requires-Dist: certifi>=2025.8.3
Requires-Dist: cffi>=1.17.1
Requires-Dist: coloredlogs>=15.0.1
Requires-Dist: h11>=0.16.0
Requires-Dist: humanfriendly>=10.0
Requires-Dist: idna>=3.10
Requires-Dist: outcome>=1.3.0.post0
Requires-Dist: pycparser>=2.22
Requires-Dist: pydantic>=2.11.7
Requires-Dist: pydantic_core>=2.33.2
Requires-Dist: pyreadline3>=3.5.4
Requires-Dist: PySocks>=1.7.1
Requires-Dist: selenium>=4.34.2
Requires-Dist: sniffio>=1.3.1
Requires-Dist: sortedcontainers>=2.4.0
Requires-Dist: soupsieve>=2.7
Requires-Dist: trio>=0.30.0
Requires-Dist: trio-websocket>=0.12.2
Requires-Dist: typing-inspection>=0.4.1
Requires-Dist: typing_extensions>=4.14.1
Requires-Dist: urllib3>=2.5.0
Requires-Dist: websocket-client>=1.8.0
Requires-Dist: wsproto>=1.2.0
Provides-Extra: dev
Requires-Dist: pytest>=6.0; extra == "dev"
Requires-Dist: pytest-asyncio; extra == "dev"
Requires-Dist: black; extra == "dev"
Requires-Dist: flake8; extra == "dev"
Requires-Dist: mypy; extra == "dev"
Requires-Dist: twine; extra == "dev"
Requires-Dist: build; extra == "dev"
Provides-Extra: test
Requires-Dist: pytest>=6.0; extra == "test"
Requires-Dist: pytest-asyncio; extra == "test"
Dynamic: license-file
